flask_dependency/__init__.py
flask_dependency/background_task.py
flask_dependency/depends.py
flask_dependency/exceptions/unprocessable_content.py
flask_dependency/form.py
flask_dependency/inject.py
flask_dependency/query.py
flask_dependency/route.py
flask_dependency/validate_schema.py
flask_dependency-0.3.0.dist-info/METADATA
flask_dependency-0.3.0.dist-info/WHEEL
flask_dependency-0.3.0.dist-info/RECORD
