Metadata-Version: 2.4
Name: flask_dependency
Version: 0.3.0
Summary: 
Author: ventura94
Author-email: arianventura94@gmail.com
Requires-Python: >=3.10,<4.0
Classifier: Programming Language :: Python :: 3
Classifier: Programming Language :: Python :: 3.10
Classifier: Programming Language :: Python :: 3.11
Classifier: Programming Language :: Python :: 3.12
Classifier: Programming Language :: Python :: 3.13
Classifier: Programming Language :: Python :: 3.14
Requires-Dist: flask (>=2.3.3,<3.0.0)
Requires-Dist: pydantic[dotenv] (>=1.10.19,<2.0.0)
